chunklet/__init__.py
chunklet/base_chunker.py
chunklet/cli.py
chunklet/exceptions.py
chunklet/plain_text_chunker.py
chunklet/code_chunker/__init__.py
chunklet/code_chunker/_code_structure_extractor.py
chunklet/code_chunker/code_chunker.py
chunklet/code_chunker/helpers.py
chunklet/code_chunker/patterns.py
chunklet/common/__init__.py
chunklet/common/batch_runner.py
chunklet/common/path_utils.py
chunklet/common/token_utils.py
chunklet/common/validation.py
chunklet/document_chunker/__init__.py
chunklet/document_chunker/document_chunker.py
chunklet/document_chunker/registry.py
chunklet/document_chunker/converters/__init__.py
chunklet/document_chunker/converters/html_2_md.py
chunklet/document_chunker/converters/latex_2_md.py
chunklet/document_chunker/converters/rst_2_md.py
chunklet/document_chunker/converters/table_2_md.py
chunklet/document_chunker/processors/__init__.py
chunklet/document_chunker/processors/base_processor.py
chunklet/document_chunker/processors/docx_processor.py
chunklet/document_chunker/processors/epub_processor.py
chunklet/document_chunker/processors/odt_processor.py
chunklet/document_chunker/processors/pdf_processor.py
chunklet/sentence_splitter/__init__.py
chunklet/sentence_splitter/_fallback_splitter.py
chunklet/sentence_splitter/languages.py
chunklet/sentence_splitter/registry.py
chunklet/sentence_splitter/sentence_splitter.py
chunklet/sentence_splitter/terminators.py
chunklet/visualizer/__init__.py
chunklet/visualizer/visualizer.py
chunklet/visualizer/static/index.html
chunklet/visualizer/static/css/style.css
chunklet/visualizer/static/js/app.js
chunklet/visualizer/static/js/utils.js
chunklet_py-2.1.1.dist-info/licenses/LICENSE
chunklet_py-2.1.1.dist-info/METADATA
chunklet_py-2.1.1.dist-info/WHEEL
chunklet_py-2.1.1.dist-info/entry_points.txt
chunklet_py-2.1.1.dist-info/top_level.txt
chunklet_py-2.1.1.dist-info/RECORD
