Metadata-Version: 2.4
Name: chunklet-py
Version: 2.1.1
Summary: Advanced text, code, and document chunking for LLM applications. Split content semantically, visualize chunks interactively, and process multiple file formats with flexible, context-aware segmentation.
Author-email: speedyk_005 <speedy40115719@gmail.com>
License-Expression: MIT
Project-URL: Homepage, https://github.com/speedyk-005/chunklet-py
Project-URL: Repository, https://github.com/speedyk-005/chunklet-py
Project-URL: Documentation, https://speedyk-005.github.io/chunklet-py/
Project-URL: Issues, https://github.com/speedyk-005/chunklet-py/issues
Project-URL: Changelog, https://github.com/speedyk-005/chunklet-py/blob/main/CHANGELOG.md
Keywords: nlp,chunking,text-splitting,sentence-splitting,llm,rag,ai,multilingual,text processing,natural language processing,data processing,information retrieval,semantic search,document processing,document-chunker,code chunking,code-chunker,source code analysis,programming languages,code structure,chunk-visualization
Classifier: Development Status :: 5 - Production/Stable
Classifier: Intended Audience :: Developers
Classifier: Intended Audience :: Science/Research
Classifier: Intended Audience :: Information Technology
Classifier: Operating System :: OS Independent
Classifier: Programming Language :: Python :: 3.10
Classifier: Programming Language :: Python :: 3.11
Classifier: Programming Language :: Python :: 3.12
Classifier: Programming Language :: Python :: 3.13
Classifier: Programming Language :: Python :: 3.14
Classifier: Topic :: Text Processing
Classifier: Topic :: Scientific/Engineering :: Artificial Intelligence
Classifier: Topic :: Software Development :: Libraries :: Python Modules
Requires-Python: >=3.10
License-File: LICENSE
Requires-Dist: pysbd>=0.3.4
Requires-Dist: sentsplit>=1.0.7
Requires-Dist: sentencex<=0.6.1
Requires-Dist: indic-nlp-library>=0.90
Requires-Dist: py3langid>=0.3.0
Requires-Dist: mpire>=2.10.0
Requires-Dist: python-box>=7.3.0
Requires-Dist: more-itertools>=10.6.0
Requires-Dist: regex>=2024.11.6
Requires-Dist: pydantic>=2.11
Requires-Dist: typer>=0.19.0
Provides-Extra: document
Requires-Dist: pdfminer.six>=20250324; extra == "document"
Requires-Dist: python-docx>=1.2.0; extra == "document"
Requires-Dist: mammoth>=1.9.0; extra == "document"
Requires-Dist: ebooklib>=0.19; extra == "document"
Requires-Dist: docutils>=0.21.2; extra == "document"
Requires-Dist: markdownify>=1.1.0; extra == "document"
Requires-Dist: striprtf>=0.0.29; extra == "document"
Requires-Dist: pylatexenc>=2.10; extra == "document"
Requires-Dist: odfpy>=1.4.1; extra == "document"
Requires-Dist: openpyxl>=3.1.2; extra == "document"
Requires-Dist: tabulate2>=1.10.0; extra == "document"
Requires-Dist: charset-normalizer>=3.4.0; extra == "document"
Provides-Extra: code
Requires-Dist: defusedxml>=0.7.1; extra == "code"
Requires-Dist: littletree>=0.8.4; extra == "code"
Requires-Dist: charset-normalizer>=3.4.0; extra == "code"
Provides-Extra: visualization
Requires-Dist: uvicorn>=0.34.0; extra == "visualization"
Requires-Dist: fastapi>=0.115.12; extra == "visualization"
Requires-Dist: python-multipart>=0.0.20; extra == "visualization"
Requires-Dist: aiofiles>=24.1.0; extra == "visualization"
Requires-Dist: charset-normalizer>=3.4.0; extra == "visualization"
Provides-Extra: all
Requires-Dist: chunklet-py[code,document,visualization]; extra == "all"
Provides-Extra: dev
Requires-Dist: pytest>=8.3.5; extra == "dev"
Requires-Dist: pytest-cov>=6.2.1; extra == "dev"
Requires-Dist: pytest-mock>=3.14.1; extra == "dev"
Requires-Dist: black>=25.1.0; extra == "dev"
Requires-Dist: flake8>=7.3.0; extra == "dev"
Requires-Dist: flake8-pyproject>=1.2.3; extra == "dev"
Provides-Extra: docs
Requires-Dist: mike>=2.1.2; extra == "docs"
Requires-Dist: mkdocs-material>=9.6.20; extra == "docs"
Requires-Dist: mkdocs-api-autonav>=0.4.0; extra == "docs"
Requires-Dist: mkdocstrings-python>=1.17.0; extra == "docs"
Requires-Dist: pymdown-extensions>=10.16.1; extra == "docs"
Provides-Extra: dev-all
Requires-Dist: chunklet-py[code,dev,docs,document,visualization]; extra == "dev-all"
Dynamic: license-file
